{"36915834":{"location":[50.5537035,8.5255199],"tp":"CL","ts":"2025-10-27T17:32:53Z","tags":{"addr:city":"Wetzlar","addr:country":"DE","addr:housenumber":"3a","addr:postcode":"35578","addr:street":"Sportparkstraße","building":"yes","leisure":"sports_centre","name":"Cube - DAV Kletterzentrum Wetzlar","operator":"Sektion Wetzlar des Deutschen Alpenvereins e. V.","phone":"+4964414494350","toilets:wheelchair":"yes","website":"https://cube-kletterzentrum.de/","wheelchair":"limited"}},"128522926":{"location":[50.588745,8.7060586],"tp":"CL","ts":"2023-10-27T19:30:48Z","tags":{"building":"yes","fee":"no","height":"10","historic":"yes","leisure":"sports_centre","name":"Kletterbunker","roof:colour":"grey","roof:height":"10","roof:shape":"gambrel","website":"http://www.kletterbunker.de","wheelchair":"no"}},"420601058":{"location":[50.5873884,8.6582788],"tp":"CL","ts":"2024-07-10T18:10:04Z","tags":{"addr:city":"Gießen","addr:country":"DE","addr:housenumber":"10","addr:postcode":"35398","addr:street":"Lehmweg","building":"yes","leisure":"sports_centre","name":"Level 8","opening_hours":"Mo 14:00-22:30; Tu-Sa 10:00-22:30; Su 10:00-21:00","start_date":"2014","website":"https://levelacht.de/"}},"588883542":{"location":[50.5811307,8.6800232],"tp":"CL","ts":"2018-05-17T07:21:24Z","tags":{"access":"permissive","fee":"no","leisure":"pitch","name":"Boulderwand","note":"überdachte Boulderwand"}},"849813962":{"location":[50.6012434,8.6931496],"tp":"CL","ts":"2021-06-29T15:04:30Z","tags":{"access":"permissive","fee":"no","leisure":"pitch","lit":"yes","name":"Kletterwand","playground":"climbingframe"}},"5196528194":{"location":[50.5900502,8.6751249],"tp":"CL","ts":"2017-10-28T16:29:37Z","tags":{"leisure":"pitch"}},"5196528195":{"location":[50.5923319,8.6837214],"tp":"CL","ts":"2017-10-28T16:29:37Z","tags":{"leisure":"pitch"}},"13301991297":{"location":[50.5820574,8.6287237],"tp":"CL","ts":"2025-11-13T16:50:40Z","tags":{"leisure":"sports_centre"}}}