{"88746106":{"location":[47.7641383,12.3433968],"tp":"CL","tags":{"name":"Geißstiegwand","natural":"cliff"}},"113391137":{"location":[47.7596305,12.3699509],"tp":"CL","tags":{"climbing:grade:uiaa:mean":"6","climbing:grade:uiaa:min":"4","climbing:multipitch":"yes","climbing:sport":"yes","name":"Steinlingwand","natural":"cliff"}},"173640289":{"location":[47.78265425,12.333514950000001],"tp":"CL","tags":{"leisure":"pitch","name":"Chiemgauer Hochseilgarten"}},"288447334":{"location":[47.860793099999995,12.641039],"tp":"CL","tags":{"access":"customers","barrier":"fence","building":"no","fee":"yes","leisure":"sports_centre","name":"Kletterturm Traunstein","opening_hours":"24/7","operator":"DAV Traunstein","operator:type":"private_non_profit","website":"https://www.alpenverein-traunstein.de/stuetzpunkte/kletterturm"}},"619767973":{"location":[47.7554172,12.3624773],"tp":"CL","tags":{"climbing":"route","climbing:grade:uiaa":"6-","name":"Kampenwandüberschreitung"}},"994006829":{"location":[47.7546588,12.3566338],"tp":"CL","tags":{"natural":"bare_rock"}},"1313014934":{"location":[47.7601531,12.3717159],"tp":"CL","tags":{"name":"Hüttenwandl","natural":"cliff"}},"1772512528":{"location":[47.7553481,12.3622131],"tp":"CL","tags":{"ele":"1645","name":"Kampenwand-Westgipfel"}},"1997401501":{"location":[47.7551197,12.3098704],"tp":"CL","tags":{}},"2490047553":{"location":[47.7866732,12.5508081],"tp":"CL","tags":{"ele":"972","name":"Engelstein","summit:cross":"yes","summit:register":"yes"}},"3129340429":{"location":[47.8609312,12.6413191],"tp":"CL","tags":{"entrance":"yes"}},"5856599612":{"location":[47.7555138,12.364489],"tp":"CL","tags":{"name":"Kampenwand-Vorgipfel"}},"5939707661":{"location":[47.8093934,12.381801],"tp":"CL","tags":{"addr:city":"Bernau am Chiemsee","addr:housenumber":"17","addr:postcode":"83233","addr:street":"Buchenstraße","leisure":"sports_centre","name":"DAV Kletterhalle Bernau","phone":"+49 8051 9614920"}},"7008929005":{"location":[47.758026,12.5416037],"tp":"CL","tags":{"climbing":"crag"}},"9375840192":{"location":[47.755481,12.3635876],"tp":"CL","tags":{"name":"Teufelsturm"}},"9375840193":{"location":[47.7554812,12.3630077],"tp":"CL","tags":{"name":"Gmelchturm"}},"11196522526":{"location":[47.7561487,12.3671505],"tp":"CL","tags":{"name":"Kampendwand - Nordgipfel: Nordseite"}},"11196525519":{"location":[47.7559468,12.3669199],"tp":"CL","tags":{"name":"Kampenwand - Nordgipfel: Südseite"}}}