{"342454280":{"location":[50.4577922,6.9625124],"tp":"CL","tags":{"access":"yes","climbing:bolted":"4 m","climbing:grade:uiaa:max":"7","climbing:grade:uiaa:mean":"5","climbing:grade:uiaa:min":"2+","climbing:quality":"solid","climbing:rock":"quartzite","climbing:sport":"yes","climbing:toprope":"yes","name":"Teufelsley","natural":"cliff"}},"667023630":{"location":[50.4577925,6.9625638],"tp":"CL","tags":{"climbing":"crag","climbing:grade:uiaa:max":"?","climbing:grade:uiaa:min":"?","climbing:sport":"yes","climbing:toprope":"yes","ele":"496.0","name":"Teufelsley","wikidata":"Q2407140","wikipedia":"de:Teufelsley (Rheinland-Pfalz)"}},"967851797":{"location":[50.3350354,6.9490406],"tp":"CL","tags":{"area":"yes","description":"Nicht in Betrieb","leisure":"sports_centre"}}}