{"14600023":{"location":[44.4206189,-72.9016149],"ts":"2022-09-19T22:05:24Z","tz":-5,"tags":{"alt_name":"Bolton Upper West","climbing":"crag","climbing:grade:yds_class:max":"5.12","climbing:grade:yds_class:min":"5.4","climbing:rock":"schist","climbing:routes":"79","name":"Upper West","site":"sport","sport":"climbing","type":"site"}},"14600024":{"location":[44.3844889,-72.9119321],"ts":"2025-05-27T03:01:13Z","tz":-5,"tags":{"alt_name":"Bolton Lower West","climbing":"crag","climbing:grade:yds_class:max":"5.12","climbing:grade:yds_class:min":"5.6","climbing:rock":"schist","climbing:routes":"34","name":"Lower West","site":"sport","sport":"climbing","type":"site"}},"19335077":{"location":[44.375197,-72.8687922],"ts":"2025-07-08T14:09:45Z","tz":-5,"tags":{"climbing":"crag","name":"Dwarf Wall","sport":"climbing","type":"site"}},"19335078":{"location":[44.374294,-72.868908],"ts":"2025-07-08T14:09:45Z","tz":-5,"tags":{"climbing":"crag","name":"Cat's Ass Wall","sport":"climbing","type":"site"}},"19335079":{"location":[44.3751433,-72.868187],"ts":"2025-07-08T14:09:45Z","tz":-5,"tags":{"climbing":"crag","name":"Schoolhouse","sport":"climbing","type":"site"}},"19335154":{"location":[44.3702896,-72.8572899],"ts":"2025-07-08T14:46:53Z","tz":-5,"tags":{"climbing":"crag","name":"Immunity Wall","sport":"climbing","type":"site"}},"19335155":{"location":[44.3706417,-72.8574048],"ts":"2025-07-08T14:46:53Z","tz":-5,"tags":{"climbing":"crag","name":"Dome Top","sport":"climbing","type":"site"}},"19335156":{"location":[44.3706471,-72.8576207],"ts":"2025-07-08T14:46:53Z","tz":-5,"tags":{"climbing":"crag","name":"Neighborhood Ledge","sport":"climbing","type":"site"}},"19335157":{"location":[44.3706859,-72.8577701],"ts":"2025-07-08T14:46:53Z","tz":-5,"tags":{"climbing":"crag","name":"Pirates' Cove","sport":"climbing","type":"site"}},"19335158":{"location":[44.3707338,-72.8580211],"ts":"2025-07-08T14:46:53Z","tz":-5,"tags":{"climbing":"crag","name":"Main Wall","sport":"climbing","type":"site"}},"19335159":{"location":[44.370829,-72.8584405],"ts":"2025-07-08T14:46:53Z","tz":-5,"tags":{"climbing":"crag","name":"Railroad Yard","sport":"climbing","type":"site"}},"19335160":{"location":[44.3707826,-72.8583421],"ts":"2025-07-08T14:46:53Z","tz":-5,"tags":{"climbing":"crag","name":"Railroad Ledge","sport":"climbing","type":"site"}},"19335161":{"location":[44.3711597,-72.8588861],"ts":"2025-07-08T14:46:53Z","tz":-5,"tags":{"climbing":"crag","name":"West Side","sport":"climbing","type":"site"}},"19335162":{"location":[44.3709544,-72.8587436],"ts":"2025-07-08T14:46:53Z","tz":-5,"tags":{"climbing":"crag","name":"Bat Wall","sport":"climbing","type":"site"}},"19335163":{"location":[44.3710856,-72.8584908],"ts":"2025-07-08T14:46:53Z","tz":-5,"tags":{"climbing":"crag","name":"Cloud Nine","sport":"climbing","type":"site"}},"19335246":{"location":[44.359154,-72.8450847],"ts":"2025-07-08T15:06:08Z","tz":-5,"tags":{"climbing":"crag","name":"Bog Wall","sport":"climbing","type":"site"}},"19335247":{"location":[44.3585523,-72.8687676],"ts":"2025-07-08T15:06:08Z","tz":-5,"tags":{"climbing":"crag","name":"Thieves' Wall","sport":"climbing","type":"site"}},"19335248":{"location":[44.3902394,-72.8495556],"ts":"2025-07-08T15:06:08Z","tz":-5,"tags":{"climbing":"area","name":"Bone Mountain","sport":"climbing","type":"site"}},"19335249":{"location":[44.3735221,-72.8554345],"ts":"2025-07-08T15:06:08Z","tz":-5,"tags":{"climbing":"crag","name":"Terra Incognita","sport":"climbing","type":"site"}},"19335250":{"location":[44.3749974,-72.8661218],"ts":"2025-07-08T15:06:08Z","tz":-5,"tags":{"climbing":"crag","name":"Carcass Crag","sport":"climbing","type":"site"}},"19335251":{"location":[44.3851423,-72.8533172],"ts":"2025-07-08T15:06:08Z","tz":-5,"tags":{"climbing":"crag","name":"Revolution Wall","sport":"climbing","type":"site"}},"19335252":{"location":[44.3781685,-72.8603146],"ts":"2025-07-08T15:06:08Z","tz":-5,"tags":{"climbing":"crag","name":"82 Crag","sport":"climbing","type":"site"}},"19335275":{"location":[44.4302519,-72.89894],"ts":"2025-07-08T15:15:56Z","tz":-5,"tags":{"climbing":"crag","name":"Main Face","sport":"climbing","type":"site"}},"19335276":{"location":[44.4293914,-72.8991305],"ts":"2025-07-08T15:15:56Z","tz":-5,"tags":{"climbing":"crag","name":"Wild West Wall","sport":"climbing","type":"site"}},"19335277":{"location":[44.427812,-72.899784],"ts":"2025-07-08T15:15:56Z","tz":-5,"tags":{"climbing":"crag","name":"Upper Upper West Bolton Shoulder","sport":"climbing","type":"site"}},"585668040":{"location":[44.3751433,-72.868187],"ts":"2025-07-08T14:09:45Z","tz":-5,"tags":{"name":"Schoolhouse / Main Quarry","natural":"cliff","sport":"climbing"}},"585668041":{"location":[44.374294,-72.868908],"ts":"2025-07-08T14:09:45Z","tz":-5,"tags":{"name":"Cat's Ass Wall","natural":"cliff","sport":"climbing"}},"1096144059":{"location":[44.4278951,-72.899784],"ts":"2024-10-08T14:48:06Z","tz":-5,"tags":{"climbing":"crag","climbing:rock":"schist","climbing:sport":"no","climbing:toprope":"yes","climbing:trad":"5","name":"Upper Upper West Bolton Shoulder","natural":"cliff","sport":"climbing"}},"1096144065":{"location":[44.4293914,-72.8991997],"ts":"2024-10-08T14:48:06Z","tz":-5,"tags":{"climbing":"crag","name":"Wild West Wall","natural":"cliff","sport":"climbing"}},"1096144078":{"location":[44.4208315,-72.9015994],"ts":"2022-09-19T22:05:24Z","tz":-5,"tags":{"climbing":"route","climbing:grade:yds_class":"5.9","climbing:length":"70'","climbing:pitches":"1","climbing:sport":"yes","climbing:toprope":"no","name":"Stone Staircase","sport":"climbing"}},"1096144079":{"location":[44.4208641,-72.9016055],"ts":"2022-09-19T22:05:24Z","tz":-5,"tags":{"climbing":"route","climbing:grade:yds_class":"5.8+","climbing:length":"45'","climbing:pitches":"1","climbing:sport":"yes","climbing:toprope":"no","name":"The Big Maciejowski","sport":"climbing"}},"1096144080":{"location":[44.4203828,-72.9016323],"ts":"2022-09-19T22:05:24Z","tz":-5,"tags":{"climbing":"route","climbing:grade:yds_class":"5.8","climbing:length":"50'","climbing:pitches":"1","climbing:sport":"yes","climbing:toprope":"no","name":"Beginner's Luck","sport":"climbing"}},"1096144094":{"location":[44.3846913,-72.9120711],"ts":"2022-09-19T22:05:24Z","tz":-5,"tags":{"climbing":"route","climbing:grade:yds_class":"5.8","climbing:length":"60'","climbing:pitches":"1","climbing:toprope":"yes","climbing:trad":"yes","name":"A-Sharp","sport":"climbing"}},"1096144095":{"location":[44.3846952,-72.9120978],"ts":"2022-09-19T22:05:24Z","tz":-5,"tags":{"climbing":"route","climbing:grade:yds_class":"5.9","climbing:length":"70'","climbing:pitches":"1","climbing:toprope":"yes","climbing:trad":"yes","name":"Say Goodnight, Dick","sport":"climbing"}},"1230700359":{"location":[44.3707826,-72.8583421],"ts":"2025-07-08T14:46:53Z","tz":-5,"tags":{"name":"Railroad Ledge","natural":"cliff","sport":"climbing"}},"1230700360":{"location":[44.3707338,-72.8580211],"ts":"2025-07-08T14:46:53Z","tz":-5,"tags":{"name":"Main Wall","natural":"cliff","sport":"climbing"}},"1230700363":{"location":[44.3709544,-72.8587436],"ts":"2025-07-08T14:46:53Z","tz":-5,"tags":{"name":"Bat Wall","natural":"cliff","sport":"climbing"}},"1230700365":{"location":[44.3706417,-72.8574048],"ts":"2025-07-08T14:46:53Z","tz":-5,"tags":{"name":"Dome Top","natural":"cliff","sport":"climbing"}},"1230700369":{"location":[44.3702896,-72.8572899],"ts":"2025-07-08T14:46:53Z","tz":-5,"tags":{"name":"Immunity Wall","natural":"cliff","sport":"climbing"}},"1322162585":{"location":[44.4302519,-72.89894],"ts":"2024-10-08T14:48:06Z","tz":-5,"tags":{"climbing":"crag","name":"Main Face","natural":"cliff","sport":"climbing"}},"1322162586":{"location":[44.42763,-72.8997657],"ts":"2024-10-08T14:48:06Z","tz":-5,"tags":{"climbing":"route","climbing:bolts":"1","climbing:grade:yds_class":"5.5","climbing:length":"39","climbing:pitches":"2","climbing:trad":"yes","name":"Shitney GIlman"}},"1322162587":{"location":[44.4291604,-72.8990927],"ts":"2024-10-08T14:48:06Z","tz":-5,"tags":{"climbing":"route","climbing:bolts":"13","climbing:grade:yds_class":"5.6","climbing:length":"42","climbing:trad":"yes","name":"Silent Nights"}},"1389965655":{"location":[44.3842779,-72.9118056],"ts":"2025-05-27T03:01:13Z","tz":-5,"tags":{"climbing":"route","climbing:grade:yds_class":"5.8","climbing:length":"90'","climbing:pitches":"1","climbing:toprope":"yes","climbing:trad":"yes","name":"Hush Momma Thrush","sport":"climbing"}},"1411925634":{"location":[44.3585523,-72.8687676],"ts":"2025-07-03T16:03:24Z","tz":-5,"tags":{"name":"Thieves' Wall","natural":"cliff","sport":"climbing"}},"1413056495":{"location":[44.3735221,-72.8554345],"ts":"2025-07-08T15:06:08Z","tz":-5,"tags":{"name":"Terra Incognita","natural":"cliff","sport":"climbing"}},"1413056513":{"location":[44.3749974,-72.8661218],"ts":"2025-07-08T15:06:08Z","tz":-5,"tags":{"name":"Carcass Crag","natural":"cliff","sport":"climbing"}},"1413056548":{"location":[44.3851423,-72.8533172],"ts":"2025-07-07T15:49:07Z","tz":-5,"tags":{"climbing:sport":"yes","climbing:trad":"yes","name":"Revolution Wall","natural":"cliff","sport":"climbing"}},"1413056550":{"location":[44.3781685,-72.8603146],"ts":"2025-07-07T15:49:07Z","tz":-5,"tags":{"climbing:sport":"yes","climbing:trad":"yes","name":"82 Crag","natural":"cliff","sport":"climbing"}},"1413269784":{"location":[44.375197,-72.8687977],"ts":"2025-07-08T14:09:45Z","tz":-5,"tags":{"name":"Dwarf Wall","natural":"cliff","sport":"climbing"}},"1413278334":{"location":[44.3706471,-72.8576207],"ts":"2025-07-08T14:46:53Z","tz":-5,"tags":{"name":"Neighborhood Ledge","natural":"cliff","sport":"climbing"}},"1413278335":{"location":[44.3706859,-72.8577701],"ts":"2025-07-08T14:46:53Z","tz":-5,"tags":{"name":"Pirates' Cove","natural":"cliff","sport":"climbing"}},"1413278336":{"location":[44.370829,-72.8584405],"ts":"2025-07-08T14:46:53Z","tz":-5,"tags":{"name":"Railroad Yard","natural":"cliff","sport":"climbing"}},"1413282704":{"location":[44.359154,-72.8450847],"ts":"2025-07-08T15:06:08Z","tz":-5,"tags":{"name":"Bog Wall","natural":"cliff","sport":"climbing"}},"5596422726":{"location":[44.3742234,-72.8688496],"ts":"2018-05-20T21:15:40Z","tz":-5,"tags":{"climbing":"route_bottom","climbing:grade:uiaa":"9-","climbing:length":"9","climbing:sport":"yes","name":"Off Night","sport":"climbing"}},"5596503631":{"location":[44.3751078,-72.8687261],"ts":"2023-02-22T02:16:50Z","tz":-5,"tags":{"climbing":"route_bottom","climbing:grade:uiaa":"5+","climbing:length":"14","climbing:sport":"yes","name":"Happy","sport":"climbing"}},"5596503634":{"location":[44.3751805,-72.8686873],"ts":"2023-02-22T02:16:50Z","tz":-5,"tags":{"climbing":"route_bottom","climbing:grade:uiaa":"7","climbing:length":"12","climbing:sport":"yes","name":"Anxious","sport":"climbing"}},"5596503635":{"location":[44.3752391,-72.8686413],"ts":"2023-02-22T02:16:50Z","tz":-5,"tags":{"climbing":"route_bottom","climbing:grade:uiaa":"5+","climbing:length":"14","climbing:sport":"yes","climbing:toprope":"yes","name":"Dopey","sport":"climbing"}},"5596503636":{"location":[44.375298,-72.868633],"ts":"2023-02-22T02:16:50Z","tz":-5,"tags":{"climbing":"route_bottom","climbing:grade:uiaa":"5","climbing:length":"9","climbing:trad":"yes","name":"Duckling","sport":"climbing"}},"5596503637":{"location":[44.3753744,-72.8686255],"ts":"2023-02-22T02:16:50Z","tz":-5,"tags":{"climbing":"route_bottom","climbing:grade:uiaa":"5","climbing:length":"12","climbing:sport":"yes","name":"Wandering the Halls","sport":"climbing"}},"5596503638":{"location":[44.3754151,-72.8686049],"ts":"2023-02-22T02:16:50Z","tz":-5,"tags":{"climbing":"route_bottom","climbing:grade:uiaa":"5+","climbing:length":"14","climbing:sport":"yes","name":"Playground Bully","sport":"climbing"}},"5596503639":{"location":[44.3754359,-72.8685712],"ts":"2023-02-22T02:16:50Z","tz":-5,"tags":{"climbing":"route_bottom","climbing:grade:uiaa":"5","climbing:length":"15.25","climbing:sport":"yes","name":"Where's The Wrench?","sport":"climbing"}},"5596503640":{"location":[44.3754557,-72.8685194],"ts":"2023-02-22T02:16:50Z","tz":-5,"tags":{"climbing":"route_bottom","climbing:grade:uiaa":"5+","climbing:length":"15.25","climbing:sport":"yes","name":"I Thought You Had It","sport":"climbing"}},"5596503641":{"location":[44.375442,-72.8684855],"ts":"2023-02-22T02:16:50Z","tz":-5,"tags":{"climbing":"route_bottom","climbing:grade:uiaa":"5-","climbing:length":"18.25","climbing:sport":"yes","name":"Anything For An A","sport":"climbing"}},"5596503642":{"location":[44.3751102,-72.8681256],"ts":"2023-02-22T02:16:50Z","tz":-5,"tags":{"climbing":"route_bottom","climbing:grade:uiaa":"7","climbing:length":"24.5","climbing:sport":"yes","name":"Collateral Daveage","sport":"climbing"}},"5596503643":{"location":[44.3750897,-72.8679792],"ts":"2023-02-22T02:16:50Z","tz":-5,"tags":{"climbing":"route_bottom","climbing:grade:uiaa":"5+","climbing:length":"30.5","climbing:sport":"yes","name":"Junior's First Bolt","sport":"climbing"}},"5596503644":{"location":[44.3743475,-72.8691072],"ts":"2018-05-20T21:15:39Z","tz":-5,"tags":{"climbing":"route_bottom","climbing:grade:uiaa":"9+","climbing:length":"7.5","climbing:trad":"yes","name":"Eye of the Cougar","sport":"climbing"}},"5596503645":{"location":[44.374317,-72.8690472],"ts":"2018-05-20T21:15:39Z","tz":-5,"tags":{"climbing":"route_bottom","climbing:grade:uiaa":"7","climbing:length":"9","climbing:trad":"yes","name":"It's only Interment","sport":"climbing"}},"5596503646":{"location":[44.3742859,-72.868982],"ts":"2018-05-20T21:15:39Z","tz":-5,"tags":{"climbing":"route_bottom","climbing:grade:uiaa":"8","climbing:length":"9","climbing:sport":"yes","name":"The Cat's Ass","sport":"climbing"}},"5596503647":{"location":[44.374254,-72.8689146],"ts":"2018-05-20T21:15:40Z","tz":-5,"tags":{"climbing":"route_bottom","climbing:grade:uiaa":"7-","climbing:length":"9","climbing:sport":"yes","name":"Cat's Night","sport":"climbing"}},"10038183757":{"location":[44.4208313,-72.9016462],"ts":"2022-09-19T22:05:24Z","tz":-5,"tags":{"climbing":"route_top"}},"10038183758":{"location":[44.4208317,-72.9015527],"ts":"2022-09-19T22:05:24Z","tz":-5,"tags":{"climbing":"route_bottom"}},"10038183759":{"location":[44.420864,-72.9016523],"ts":"2022-09-19T22:05:24Z","tz":-5,"tags":{"climbing":"route_top"}},"10038183760":{"location":[44.4208643,-72.9015588],"ts":"2022-09-19T22:05:24Z","tz":-5,"tags":{"climbing":"route_bottom"}},"10038183761":{"location":[44.420392,-72.901677],"ts":"2022-09-19T22:05:24Z","tz":-5,"tags":{"climbing":"route_top"}},"10038183762":{"location":[44.4203735,-72.9015875],"ts":"2022-09-19T22:05:24Z","tz":-5,"tags":{"climbing":"route_bottom"}},"10038183833":{"location":[44.3847196,-72.9120691],"ts":"2022-09-19T22:05:24Z","tz":-5,"tags":{"climbing":"route_top"}},"10038183834":{"location":[44.3846629,-72.912073],"ts":"2022-09-19T22:05:24Z","tz":-5,"tags":{"climbing":"route_bottom"}},"10038183836":{"location":[44.3847248,-72.9120775],"ts":"2022-09-19T22:05:24Z","tz":-5,"tags":{"climbing":"route_top"}},"10038183837":{"location":[44.3846656,-72.9121181],"ts":"2022-09-19T22:05:24Z","tz":-5,"tags":{"climbing":"route_bottom"}},"12235184125":{"location":[44.4275175,-72.8997187],"ts":"2024-10-08T14:48:06Z","tz":-5,"tags":{"climbing":"route_bottom"}},"12235184128":{"location":[44.4277425,-72.8998221],"ts":"2024-10-08T14:48:06Z","tz":-5,"tags":{"climbing":"route_top"}},"12235184129":{"location":[44.4275665,-72.8997478],"ts":"2024-10-08T14:48:06Z","tz":-5,"tags":{"climbing":"bolt"}}}