{"833910818":{"location":[51.621104,-4.2273548],"tp":"CL","tags":{"leisure":"Traditional Crag","name":"Main Slab"}},"1033914844":{"location":[51.75104945,-4.56968855],"tp":"CL","tags":{"leisure":"abseil_tower"}},"1274242617":{"location":[51.6211059,-4.2280239],"tp":"CL","tags":{"leisure":"Traditional Crag","name":"Tor Gro - Hidden Slab"}},"1274242621":{"location":[51.622161,-4.236871],"tp":"CL","tags":{"leisure":"Traditional Crag","name":"North Hill Tor"}},"1334435944":{"location":[51.6211535,-4.2285287],"tp":"CL","tags":{"leisure":"Traditional Crag","name":"Bone Buttress"}},"1809665092":{"location":[51.620499,-4.226668],"tp":"CL","tags":{"leisure":"Traditional Crag","name":"Overhang Slab"}}}