{"2628201529":{"location":[57.9764118,56.1578464],"ts":"2022-05-26T14:30:20Z","tz":6,"tags":{"climbing:boulder":"yes","climbing:sport":"yes","climbing:toprope":"yes","contact:vk":"https://vk.com/skalaperm","fee":"yes","leisure":"sports_centre","name":"Скала","phone":"+7 982 4551596","sport":"climbing","website":"https://skalaclub.ru/"}},"3100272811":{"location":[58.0022292,55.9398108],"ts":"2019-03-06T00:07:23Z","tz":6,"tags":{"climbing:boulder":"yes","contact:vk":"https://vk.com/club48761894","email":"igorkivilev@mail.ru","fee":"yes","leisure":"sports_centre","name":"Геккон","opening_hours":"Mo-Su 17:00-21:30","phone":"+7 909 1010894","sport":"climbing","website":"https://gekkon59.nethouse.ru/"}}}