{"435217153":{"location":[38.6364493,-0.8527203],"tp":"CL","tags":{"highway":"via_ferrata","name":"Vía ferrata Castillo de Salvatierra","via_ferrata_scale":"2"}},"435217155":{"location":[38.6361909,-0.8522611],"tp":"CL","tags":{"highway":"via_ferrata","name":"Vía ferrata Sierra de la Villa","via_ferrata_scale":"2"}},"490266840":{"location":[38.6157655,-0.7162927],"tp":"CL","tags":{"climbing:bolted":"yes","climbing:grade:french:max":"7a+","climbing:grade:french:min":"IV+","climbing:multipitch":"no","climbing:orientation":"S","climbing:quality":"solid","climbing:rock":"limestone","climbing:routes":"40","climbing:sport":"yes","climbing:toprope":"yes","climbing:trad":"no","name":"Reconco, Penyes de Sauro","natural":"cliff"}},"533266259":{"location":[38.6163046,-0.7127783],"tp":"CL","tags":{"climbing:bolted":"yes","climbing:grade:french:max":"7b","climbing:grade:french:min":"IV","climbing:multipitch":"no","climbing:orientation":"S","climbing:quality":"solid","climbing:rock":"limestone","climbing:routes":"10","climbing:sport":"yes","climbing:toprope":"yes","climbing:trad":"yes","name":"Reconco, Pared de Torriá","natural":"cliff"}},"544912761":{"location":[38.6044817,-0.798279],"tp":"CL","tags":{"climbing:bolted":"yes","climbing:grade:french:max":"8a+","climbing:grade:french:min":"IV+","climbing:multipitch":"no","climbing:orientation":"O","climbing:quality":"solid","climbing:rock":"limestone","climbing:routes":"70","climbing:sport":"yes","climbing:toprope":"yes","climbing:trad":"no","name":"Peña Rubia","natural":"cliff"}},"658494926":{"location":[38.6365342,-0.8523687],"tp":"CL","tags":{"highway":"via_ferrata"}},"658494929":{"location":[38.6367738,-0.8527977],"tp":"CL","tags":{"highway":"via_ferrata","name":"Vía ferrata Castillo de Salvatierra","via_ferrata_scale":"2"}},"1115991867":{"location":[38.7213721,-1.0372655],"tp":"CL","tags":{"climbing:grade:french:max":"6c","climbing:grade:french:min":"4a","climbing:orientation":"S","climbing:quality":"fragile","climbing:rock":"limestone","climbing:routes":"40","climbing:sport":"yes","climbing:toprope":"yes","height":"25","name":"La Cantera","natural":"cliff"}},"1164752694":{"location":[38.6060956,-0.7921033],"tp":"CL","tags":{"climbing:orientation":"N","climbing:quality":"medium","climbing:rock":"limestone","climbing:sport":"yes","climbing:toprope":"yes","name":"El Parking","natural":"cliff","outdoor":"yes"}},"1164756822":{"location":[38.6077536,-0.791316],"tp":"CL","tags":{"climbing:orientation":"N","climbing:quality":"medium","climbing:rock":"limestone","climbing:sport":"yes","climbing:toprope":"yes","natural":"cliff","outdoor":"yes"}},"1164756823":{"location":[38.6069298,-0.791721],"tp":"CL","tags":{"climbing:orientation":"N","climbing:quality":"medium","climbing:rock":"limestone","climbing:sport":"yes","climbing:toprope":"yes","natural":"cliff","outdoor":"yes"}},"1459422140":{"location":[38.7359666,-1.0249144],"tp":"CL","tags":{"highway":"via_ferrata","via_ferrata_scale":"0"}},"1459422141":{"location":[38.7357229,-1.0247481],"tp":"CL","tags":{"highway":"via_ferrata","via_ferrata_scale":"0"}},"1459422142":{"location":[38.7359588,-1.0237504],"tp":"CL","tags":{"highway":"via_ferrata","via_ferrata_scale":"1"}},"1459422143":{"location":[38.7359395,-1.0237484],"tp":"CL","tags":{"highway":"via_ferrata","via_ferrata_scale":"1"}},"1459422145":{"location":[38.7366785,-1.0255772],"tp":"CL","tags":{"highway":"via_ferrata","incline":"up","via_ferrata_scale":"3"}},"1459422146":{"location":[38.7366581,-1.0255543],"tp":"CL","tags":{"highway":"via_ferrata","incline":"up","via_ferrata_scale":"5"}},"1459422148":{"location":[38.7362555,-1.0247041],"tp":"CL","tags":{"highway":"via_ferrata","incline":"up","via_ferrata_scale":"3"}},"1459422149":{"location":[38.736145449999995,-1.024803],"tp":"CL","tags":{"bridge":"yes","bridge:structure":"simple-suspension","cable_number":"3","description":"Puente mono","highway":"via_ferrata","layer":"1"}},"1459422150":{"location":[38.7358518,-1.0248114],"tp":"CL","tags":{"highway":"via_ferrata","incline":"up","via_ferrata_scale":"3"}},"1459422151":{"location":[38.73582145,-1.0245321],"tp":"CL","tags":{"aerialway":"zip_line","highway":"via_ferrata"}},"1459422152":{"location":[38.7359669,-1.0240465],"tp":"CL","tags":{"highway":"via_ferrata","via_ferrata_scale":"0"}},"1459422153":{"location":[38.7359309,-1.0236258],"tp":"CL","tags":{"highway":"via_ferrata","incline":"up","via_ferrata_scale":"6"}},"1459422154":{"location":[38.7359196,-1.023645],"tp":"CL","tags":{"highway":"via_ferrata","incline":"up","via_ferrata_scale":"3"}},"1459422155":{"location":[38.7357841,-1.0234785],"tp":"CL","tags":{"highway":"via_ferrata","incline":"up","via_ferrata_scale":"2"}},"1459422156":{"location":[38.7354191,-1.0238179],"tp":"CL","tags":{"bridge":"yes","bridge:structure":"simple-suspension","cable_number":"4","description":"Puente tibetano","highway":"via_ferrata","layer":"1"}},"1459422157":{"location":[38.7351854,-1.0239998],"tp":"CL","tags":{"highway":"via_ferrata","incline":"up","via_ferrata_scale":"2"}},"13376889601":{"location":[38.7351039,-1.0240104],"tp":"CL","tags":{"name":"Vía Ferrata Sierra Oliva","via_ferrata":"start"}}}