{"16489236":{"lat":41.9351815,"lon":-8.2233303,"ts":"2023-10-14T11:59:29Z","tz":0,"tags":{"alt_name":"Fraga das Pastorinhas","climbing":"crag","climbing:grade:french:max":"6b+","climbing:grade:french:min":"4c","climbing:multipitch":"7","climbing:orientation":"SW","climbing:rock":"granite","climbing:trad":"7","description":"Granite rock face with trad climbing routes. Highest single face in Portugal.","ele":"910","name":"Fraga da Nédia","natural":"bare_rock","sport":"climbing"}},"16795466":{"lat":42.0093399,"lon":-8.1285871,"ts":"2023-12-09T18:34:00Z","tz":0,"tags":{"alt_name":"Fraga de Numão","climbing":"crag","climbing:grade:french:max":"7a","climbing:grade:french:min":"6b+","climbing:multipitch":"4","climbing:rock":"granite","climbing:trad":"4","name":"Fraga de Anamão","natural":"bare_rock","sport":"climbing"}},"18283792":{"lat":41.9754594,"lon":-8.2226854,"ts":"2024-11-13T19:01:49Z","tz":0,"tags":{"climbing":"crag","name":"Crag with wooden terrace","site":"climbing","sport":"climbing","type":"site","wikimedia_commons":"File:Peneda rocks - crag with wooden terrace.jpg"}},"18283793":{"lat":41.97667,"lon":-8.22447,"ts":"2024-11-13T19:01:49Z","tz":0,"tags":{"climbing":"area","name":"Meadinha Peneda","site":"climbing","type":"site"}},"1060297955":{"lat":41.8506811,"lon":-8.1774531,"ts":"2023-09-17T10:07:21Z","tz":1,"tags":{"climbing":"crag","climbing:multipitch":"1","climbing:rock":"granite","climbing:trad":"1","name":"Torre Pequena","natural":"bare_rock","sport":"climbing"}},"12318172802":{"lat":41.9754672,"lon":-8.22267,"ts":"2024-11-14T08:52:13Z","tz":0,"tags":{"climbing":"route_bottom","climbing:grade:uiaa":"~7-","climbing:length":"8m","sport":"climbing","wikimedia_commons":"File:Peneda rocks - crag with wooden terrace.jpg","wikimedia_commons:path":"0.52,0.89|0.477,0.518B|0.488,0.377B|0.482,0.29B|0.487,0.158B|0.476,0.1A"}},"12318180201":{"lat":41.9754516,"lon":-8.2227007,"ts":"2024-11-14T08:52:13Z","tz":0,"tags":{"climbing":"route_bottom","climbing:grade:uiaa":"~7","climbing:length":"8m","sport":"climbing","wikimedia_commons":"File:Peneda rocks - crag with wooden terrace.jpg","wikimedia_commons:path":"0.368,0.888|0.348,0.607B|0.377,0.492B|0.377,0.39B|0.352,0.31B|0.365,0.262A"}},"12318831301":{"lat":41.97667,"lon":-8.22447,"ts":"2024-11-13T19:01:49Z","tz":0,"tags":{"climbing":"crag","name":"Meadinha Peneda","sport":"climbing","website":"http://meadinha.com/"}}}