{"13393546":{"location":[47.1727257,15.3160984],"ts":"2021-11-01T12:40:21Z","tz":1,"tags":{"climbing":"crag","name":"Pfaffenkogel","type":"site"}},"105286357":{"location":[47.2066338,15.3496428],"ts":"2024-03-12T11:08:34Z","tz":1,"tags":{"name":"Peggauer Wand","natural":"cliff","sport":"climbing","wikidata":"Q1781341","wikimedia_commons":"Category:Peggauer Wand","wikipedia":"de:Peggauer Wand"}},"165396315":{"location":[47.1387026,15.3295673],"ts":"2020-11-27T18:42:03Z","tz":1,"tags":{"climbing:grade:french:max":"8c/8c+","climbing:grade:french:min":"6a","climbing:sport":"25","name":"Unteres Zigeunerloch","natural":"cliff","sport":"climbing","website":"https://www.bergsteigen.com/touren/klettergarten/zigeunerloch/"}},"330233249":{"location":[47.0712827,15.4354048],"ts":"2025-03-10T21:06:42Z","tz":1,"tags":{"access":"yes","covered":"yes","level":"-1","name":"Kletterwand","opening_hours":"24/7","operator":"Holding Graz","source":"Stadt Graz - data.graz.gv.at","sport":"climbing","start_date":"2003-10-11"}},"349271909":{"location":[47.0720802,15.4351762],"ts":"2025-03-10T21:06:42Z","tz":1,"tags":{"access":"permissive","covered":"yes","description":"Climbing Wall Under The Bridge","fee":"no","height":"5","layer":"-1","leisure":"sport","name":"Murpromenade Boulderwand","opening_hours":"Mo-Sa 7:00-21:00; Su, PH 8:00-21:00","playground":"climbingwall","playground:theme":"climbing","sport":"climbing"}},"370281626":{"location":[47.1765408,15.3904447],"ts":"2016-04-25T12:06:52Z","tz":1,"tags":{"name":"Hasenstein","natural":"cliff","source":"geoimage.at","sport":"climbing"}},"383473671":{"location":[47.2002308,15.3349291],"ts":"2015-11-29T16:43:26Z","tz":1,"tags":{"climbing:sport":"yes","natural":"cliff","sport":"climbing"}},"383473678":{"location":[47.2144495,15.3326076],"ts":"2020-05-24T16:17:38Z","tz":1,"tags":{"natural":"cliff","sport":"climbing","website":"http://www.chalkbag.at/de/outdoor/steiermark/bergland/huatluckn(5).pdf"}},"383473680":{"location":[47.2141685,15.3327416],"ts":"2020-05-24T16:17:38Z","tz":1,"tags":{"climbing:sport":"19","name":"Untere Huatluckn","natural":"cliff","sport":"climbing"}},"383485756":{"location":[47.2239283,15.3419786],"ts":"2021-12-26T19:40:52Z","tz":1,"tags":{"climbing:sport":"55","name":"Badlwand","natural":"cliff","sport":"climbing"}},"383485757":{"location":[47.2213282,15.3352411],"ts":"2021-03-11T20:33:18Z","tz":1,"tags":{"climbing":"no","name":"Mastkopf","natural":"cliff"}},"418378765":{"location":[47.2240005,15.337324],"ts":"2024-03-12T11:08:34Z","tz":1,"tags":{"climbing":"boulder","climbing:boulder":"yes","name":"Dumpfbackenblick","natural":"cliff","sport":"climbing"}},"503029489":{"location":[47.1727544,15.3159924],"ts":"2021-10-30T18:29:08Z","tz":1,"tags":{"natural":"cliff","sport":"climbing"}},"563681908":{"location":[47.1231328,15.357677],"ts":"2024-03-12T11:05:27Z","tz":1,"tags":{"climbing":"crag","climbing:bolted":"yes","climbing:rock":"limestone","name":"Waldspielplatz","natural":"cliff","sport":"climbing","website":"https://www.bergsteigen.com/touren/klettergarten/waldspielplatz-gratkorn/"}},"563681909":{"location":[47.1231511,15.3569313],"ts":"2024-03-12T11:05:27Z","tz":1,"tags":{"climbing":"crag","climbing:bolted":"yes","climbing:rock":"limestone","name":"Waldspielplatz","natural":"cliff","sport":"climbing","website":"https://www.bergsteigen.com/touren/klettergarten/waldspielplatz-gratkorn/"}},"807821109":{"location":[47.2139369,15.3323838],"ts":"2020-05-24T16:17:38Z","tz":1,"tags":{"climbing:sport":"5","name":"Obere Huatluckn","natural":"cliff","sport":"climbing","website":"http://www.chalkbag.at/de/outdoor/steiermark/bergland/huatluckn(5).pdf"}},"878367500":{"location":[47.1388615,15.3302689],"ts":"2020-11-27T18:42:03Z","tz":1,"tags":{"climbing:grade:uiaa:max":"10-","climbing:grade:uiaa:min":"5-","climbing:sport":"18","name":"Oberes Zigeunerloch","natural":"cliff","sport":"climbing","website":"https://www.gbl-outdoor.com/media/topo-oberes-zigeunerloch-gratkorn-grazer-bergland-klettergarten-oberes-zigeunerloch-13403.pdf"}},"902044513":{"location":[47.2305047,15.2838358],"ts":"2021-01-30T18:11:37Z","tz":1,"tags":{"climbing:boulder":"yes","climbing:sport":"yes","natural":"cliff","sport":"climbing"}},"928938800":{"location":[47.1726373,15.3162598],"ts":"2024-07-30T15:05:07Z","tz":1,"tags":{"climbing":"route","climbing:grade:uiaa":"6","climbing:pitches":"3","name":"Grazer Weg","website":"http://www.styria-alpin.at/index_htm_files/kb-grazerweg.pdf"}},"928938801":{"location":[47.1726302,15.3162421],"ts":"2024-07-30T15:12:46Z","tz":1,"tags":{"climbing":"route","climbing:grade:uiaa":"4+","climbing:pitches":"5","name":"Rudlweg","website":"https://www.gbl-outdoor.com/tour/rudlweg-pfaffenkogel-grazer-bergland-klettern-1693"}},"984650029":{"location":[47.1727019,15.3161132],"ts":"2021-04-10T18:02:33Z","tz":1,"tags":{"climbing":"route_top"}},"1015635990":{"location":[47.2221803,15.340015],"ts":"2021-12-26T19:40:52Z","tz":1,"tags":{"climbing:sport":"55","name":"Badlwand","natural":"cliff","sport":"climbing"}},"1030489078":{"location":[47.2266484,15.3346074],"ts":"2024-03-12T11:08:34Z","tz":1,"tags":{"climbing":"boulder","name":"Welle","natural":"cliff","sport":"climbing"}},"1082673339":{"location":[47.2156284,15.3329477],"ts":"2022-07-31T12:04:36Z","tz":1,"tags":{"climbing":"route","climbing:grade:uiaa:max":"4+","name":"Scarlet's Himmelfahrt","sport":"climbing","website":"https://www.thecrag.com/de/klettern/austria/wien-vienna-area/graz-bruck-area/route/4659015282"}},"4082069657":{"location":[47.1673674,15.2776802],"ts":"2016-03-27T23:38:52Z","tz":1,"tags":{"sport":"climbing"}},"6125307621":{"location":[47.1118894,15.3958123],"ts":"2024-03-12T11:05:27Z","tz":1,"tags":{"climbing":"crag","climbing:bolted":"yes","climbing:rock":"limestone","contact:website":"https://www.bergsteigen.com/touren/klettergarten/andritz-weinzoedl-graz/","name":"Klettergarten Weinzödl","natural":"cliff","sport":"climbing"}},"7815440496":{"location":[47.0652274,15.4303891],"ts":"2024-06-24T07:29:38Z","tz":1,"tags":{"addr:city":"Graz","addr:housenumber":"18","addr:postcode":"8020","addr:street":"Ägydigasse","check_date":"2024-06-24","climbing:boulder":"yes","contact:email":"office@trikomp.at","fee":"yes","indoor":"yes","leisure":"sports_centre","name":"Newton","name:etymology:wikidata":"Q935","opening_hours":"Mo-Fr 07:00-22:00; Sa-Su 09:30-22:00","sport":"climbing","website":"https://www.newton-graz.com/"}},"8615532737":{"location":[47.1726186,15.3163429],"ts":"2021-04-10T18:02:33Z","tz":1,"tags":{"climbing":"route_bottom"}},"8615532739":{"location":[47.1726578,15.3161766],"ts":"2021-04-10T18:02:33Z","tz":1,"tags":{"climbing":"route_top"}},"8615532753":{"location":[47.172605,15.316371],"ts":"2021-04-10T18:02:33Z","tz":1,"tags":{"climbing":"route_bottom"}},"9922254108":{"location":[47.2152903,15.3332285],"ts":"2022-07-31T12:04:36Z","tz":1,"tags":{"climbing":"route_bottom"}},"9922254109":{"location":[47.2159666,15.3326668],"ts":"2022-07-31T12:04:36Z","tz":1,"tags":{"climbing":"route_top"}},"11817264698":{"location":[47.0898482,15.4230825],"ts":"2024-04-14T20:47:36Z","tz":1,"tags":{"climbing:length":"3","outdoor":"yes","sport":"climbing"}}}